subfix/__init__.py
subfix/converter/__init__.py
subfix/converter/enumerations.py
subfix/converter/exceptions.py
subfix/converter/manager.py
subfix/core/__init__.py
subfix/core/enumerations.py
subfix/core/exceptions.py
subfix/core/structs.py
subfix/utils/__init__.py
subfix/utils/exceptions.py
subfix/utils/file.py
subfix/utils/path.py
subfix/utils/string.py
subfixio-0.1.0.dist-info/LICENSE
subfixio-0.1.0.dist-info/METADATA
subfixio-0.1.0.dist-info/WHEEL
subfixio-0.1.0.dist-info/top_level.txt
subfixio-0.1.0.dist-info/RECORD
