Metadata-Version: 2.1
Name: subfixio
Version: 0.1.0
Summary: A simple subtitle encoding fixer.
Home-page: https://github.com/mononobi/subfix
Author: Mohamad Nobakht
Author-email: mohamadnobakht@gmail.com
Maintainer: Mohamad Nobakht
Maintainer-email: mohamadnobakht@gmail.com
License: GPL-3.0
Project-URL: Code, https://github.com/mononobi/subfix
Project-URL: Issue tracker, https://github.com/mononobi/subfix/issues
Keywords: subfix subfixio python movie subtitle encoding utf-8 converter batch-converter srt
Platform: UNKNOWN
Classifier: Development Status :: 5 - Production/Stable
Classifier: Environment :: Plugins
Classifier: Intended Audience :: Developers
Classifier: License :: OSI Approved :: GNU General Public License v3 (GPLv3)
Classifier: Operating System :: OS Independent
Classifier: Programming Language :: Python
Classifier: Programming Language :: Python :: 3.5
Classifier: Programming Language :: Python :: 3.6
Classifier: Programming Language :: Python :: 3.7
Classifier: Programming Language :: Python :: 3.8
Classifier: Programming Language :: Python :: 3.9
Classifier: Programming Language :: Python :: Implementation :: CPython
Classifier: Topic :: Software Development :: Libraries :: Python Modules
Classifier: Topic :: Utilities
Requires-Python: >=3.5
Requires-Dist: chardet (>=3.0.4)
Provides-Extra: tests
Requires-Dist: chardet (>=3.0.4) ; extra == 'tests'
Requires-Dist: pytest ; extra == 'tests'
Requires-Dist: pytest-cov ; extra == 'tests'
Requires-Dist: pygments ; extra == 'tests'
